cirro/__init__.py
cirro/auth/__init__.py
cirro/auth/access_token.py
cirro/auth/base.py
cirro/auth/device_code.py
cirro/auth/oauth_models.py
cirro/cirro_client.py
cirro/cli/__init__.py
cirro/cli/cli.py
cirro/cli/controller.py
cirro/cli/interactive/__init__.py
cirro/cli/interactive/auth_args.py
cirro/cli/interactive/common_args.py
cirro/cli/interactive/create_pipeline_config.py
cirro/cli/interactive/download_args.py
cirro/cli/interactive/list_dataset_args.py
cirro/cli/interactive/upload_args.py
cirro/cli/interactive/upload_reference_args.py
cirro/cli/interactive/utils.py
cirro/cli/interactive/validate_args.py
cirro/cli/models.py
cirro/clients/__init__.py
cirro/clients/s3.py
cirro/config.py
cirro/file_utils.py
cirro/helpers/__init__.py
cirro/helpers/constants.py
cirro/helpers/form.py
cirro/helpers/preprocess_dataset.py
cirro/helpers/pyodide_patch_file.py
cirro/helpers/pyodide_patch_httpx.py
cirro/helpers/references.py
cirro/models/__init__.py
cirro/models/assets.py
cirro/models/dataset.py
cirro/models/file.py
cirro/models/form_specification.py
cirro/models/process/__init__.py
cirro/models/process/nextflow.py
cirro/models/process/process.py
cirro/models/process/wdl.py
cirro/models/reference.py
cirro/models/s3_path.py
cirro/sdk/__init__.py
cirro/sdk/asset.py
cirro/sdk/dataset.py
cirro/sdk/developer.py
cirro/sdk/exceptions.py
cirro/sdk/file.py
cirro/sdk/helpers.py
cirro/sdk/login.py
cirro/sdk/portal.py
cirro/sdk/process.py
cirro/sdk/project.py
cirro/sdk/reference.py
cirro/sdk/reference_type.py
cirro/services/__init__.py
cirro/services/base.py
cirro/services/billing.py
cirro/services/compute_environment.py
cirro/services/dataset.py
cirro/services/execution.py
cirro/services/file.py
cirro/services/metadata.py
cirro/services/metrics.py
cirro/services/process.py
cirro/services/projects.py
cirro/services/references.py
cirro/services/service_helpers.py
cirro/services/share.py
cirro/services/user.py
cirro/services/workspace.py
cirro/utils.py
cirro-1.10.0.dist-info/METADATA
cirro-1.10.0.dist-info/WHEEL
cirro-1.10.0.dist-info/entry_points.txt
cirro-1.10.0.dist-info/licenses/LICENSE.txt
cirro-1.10.0.dist-info/RECORD
