Metadata-Version: 2.4
Name: cirro
Version: 1.10.0
Summary: CLI tool and SDK for interacting with the Cirro platform
License: MIT
License-File: LICENSE.txt
Author: Cirro Bio
Author-email: support@cirro.bio
Requires-Python: >3.10.0,<4.0
Classifier: License :: OSI Approved :: MIT License
Classifier: Programming Language :: Python :: 3
Classifier: Programming Language :: Python :: 3.11
Classifier: Programming Language :: Python :: 3.12
Classifier: Programming Language :: Python :: 3.13
Classifier: Programming Language :: Python :: 3.14
Provides-Extra: nextflow
Provides-Extra: pyodide
Provides-Extra: wdl
Requires-Dist: attrs (>=21.3.0)
Requires-Dist: awscrt (==0.30.0)
Requires-Dist: boto3 (>=1.41,<2.0)
Requires-Dist: cirro_api_client (>=1.3.0,<1.4.0)
Requires-Dist: click (>=8.1.3,<9.0.0)
Requires-Dist: jsonschema (>=4.21.1,<5.0.0)
Requires-Dist: miniwdl (>=1.13.0,<2.0.0) ; extra == "wdl"
Requires-Dist: msal-extensions (>=1.0.0,<2.0.0)
Requires-Dist: nf-core (>=3.3.2,<4.0.0) ; extra == "nextflow"
Requires-Dist: pandas (>=2.2.0,<3.0.0)
Requires-Dist: pyjwt (>=2.10.0,<3.0.0)
Requires-Dist: questionary (>=2.0.1,<3.0.0)
Requires-Dist: referencing (>=0.36.2,<0.37.0)
Requires-Dist: requests (>=2.32.0,<3.0.0)
Requires-Dist: requests-aws4auth (==1.3.1) ; extra == "pyodide"
Requires-Dist: s3fs (==2025.12.0)
Requires-Dist: tqdm (>=4.62.3,<5.0.0)
Project-URL: Repository, https://github.com/CirroBio/Cirro-SDK-Python
